MineDB/__init__.py
MineDB/basicCommands.py
MineDB/dataCommands.py
MineDB/main.py
minedb-1.0.2.dist-info/licenses/LICENSE
minedb-1.0.2.dist-info/METADATA
minedb-1.0.2.dist-info/WHEEL
minedb-1.0.2.dist-info/top_level.txt
minedb-1.0.2.dist-info/RECORD
