Metadata-Version: 2.4
Name: minedb
Version: 1.0.2
Summary: A lightweight encrypted local database using dictionary-based storage
Home-page: https://github.com/harshsikarwar/MineDB
Author: Harsh Singh Sikarwar
License: MIT
Project-URL: Source, https://github.com/harshsikarwar/MineDB
Project-URL: Issues, https://github.com/harshsikarwar/MineDB/issues
Classifier: Programming Language :: Python :: 3
Classifier: License :: OSI Approved :: MIT License
Classifier: Operating System :: OS Independent
Requires-Python: >=3.9
License-File: LICENSE
Requires-Dist: cryptography>=41.0.0
Dynamic: author
Dynamic: classifier
Dynamic: description
Dynamic: description-content-type
Dynamic: home-page
Dynamic: license
Dynamic: license-file
Dynamic: project-url
Dynamic: requires-dist
Dynamic: requires-python
Dynamic: summary
